[{"pk": 1, "model": "fcore.company", "fields": {"slug": "demo", "name": "demo"}}, {"pk": 2, "model": "fcore.company", "fields": {"slug": "demo-org-2", "name": "demo org 2"}}, {"pk": 3, "model": "feditor.testproject", "fields": {"name": "demo org 2 project", "created": "2012-08-19T05:06:54.278Z", "company": 2, "base_url": "http://apitester.com/api", "common_params": "", "modified": "2012-08-19T05:06:54.278Z", "slug": "demo-org-2-project"}}, {"pk": 2, "model": "feditor.testproject", "fields": {"name": "Github", "created": "2012-08-19T05:06:30.647Z", "company": 1, "base_url": "https://api.github.com/", "common_params": "", "modified": "2012-08-19T05:06:30.647Z", "slug": "github"}}, {"pk": 1, "model": "feditor.testproject", "fields": {"name": "Twitter", "created": "2012-08-19T05:04:35.044Z", "company": 1, "base_url": "http://api.twitter.com/1/", "common_params": "", "modified": "2012-08-19T05:04:35.044Z", "slug": "twitter"}}, {"pk": 1, "model": "feditor.testcase", "fields": {"login_options": {"consumer_secret": "TnnqvtkvoJqBkFMQnfoWvVxb64ERtHg1AX6mFaEo9hM", "access_token": "767416465-lrGQyTH8xX8zMZEMzCv8s1RKuAqDKXs67HKHAEPM", "consumer_key": "0i4uIl0o03YxeRU6h93pQ", "access_token_secret": "5xHHCCP3hjTenGFOgWyEFiWg0kkKWuZpnO6MvIjoE"}, "created": "2012-08-18T10:00:00Z", "modified": "2012-08-19T11:48:02.767Z", "slug": "user-timeline", "project": 1, "login_type": "oauth", "order": 1, "name": "user_timeline"}}, {"pk": 2, "model": "feditor.testcase", "fields": {"login_options": {"consumer_secret": "TnnqvtkvoJqBkFMQnfoWvVxb64ERtHg1AX6mFaEo9hM", "access_token": "767416465-lrGQyTH8xX8zMZEMzCv8s1RKuAqDKXs67HKHAEPM", "consumer_key": "0i4uIl0o03YxeRU6h93pQ", "access_token_secret": "5xHHCCP3hjTenGFOgWyEFiWg0kkKWuZpnO6MvIjoE"}, "created": "2012-08-18T10:00:00Z", "modified": "2012-08-19T11:47:58.626Z", "slug": "post-tweet", "project": 1, "login_type": "oauth", "order": 1, "name": "post tweet"}}, {"pk": 3, "model": "feditor.testcase", "fields": {"login_options": null, "created": "2012-08-19T05:13:29.210Z", "modified": "2012-08-19T05:13:29.210Z", "slug": "get-commits", "project": 2, "login_type": "none", "order": 1, "name": "get_commits"}}, {"pk": 1, "model": "feditor.testcasestep", "fields": {"url": "statuses/user_timeline.json", "testcase": 1, "params": "{\"count\": \"{random:1:d}\", \"trim_user\": \"true\", \"screen_name\": \"alarin_ru\"}", "order": 1, "method": "GET"}}, {"pk": 2, "model": "feditor.testcasestep", "fields": {"url": "statuses/update.json", "testcase": 2, "params": "{\"status\": \"{random:140}\"}", "order": 0, "method": "POST"}}, {"pk": 3, "model": "feditor.testcasestep", "fields": {"url": "statuses/user_timeline.json", "testcase": 2, "params": "", "order": 1, "method": "GET"}}, {"pk": 1, "model": "frunner.testrun", "fields": {"end_date": "2012-08-19T11:44:12.340Z", "base_url": "http://api.twitter.com/1/", "common_params": "", "project": 1, "result": "success", "start_date": "2012-08-19T11:44:10.419Z"}}, {"pk": 2, "model": "frunner.testrun", "fields": {"end_date": "2012-08-19T11:48:29.268Z", "base_url": "http://api.twitter.com/1/", "common_params": "", "project": 1, "result": "success", "start_date": "2012-08-19T11:48:27.073Z"}}, {"pk": 1, "model": "frunner.testcase", "fields": {"result": "success", "exception": null, "login_options": null, "end_date": "2012-08-19T11:44:11.247Z", "slug": "user-timeline", "start_date": "2012-08-19T11:44:10.528Z", "login_type": "none", "testrun": 1, "order": 1, "name": "user_timeline"}}, {"pk": 2, "model": "frunner.testcase", "fields": {"result": "success", "exception": null, "login_options": null, "end_date": "2012-08-19T11:44:12.214Z", "slug": "post-tweet", "start_date": "2012-08-19T11:44:11.374Z", "login_type": "none", "testrun": 1, "order": 1, "name": "post tweet"}}, {"pk": 3, "model": "frunner.testcase", "fields": {"result": "success", "exception": null, "login_options": {"consumer_secret": "TnnqvtkvoJqBkFMQnfoWvVxb64ERtHg1AX6mFaEo9hM", "access_token": "767416465-lrGQyTH8xX8zMZEMzCv8s1RKuAqDKXs67HKHAEPM", "consumer_key": "0i4uIl0o03YxeRU6h93pQ", "access_token_secret": "5xHHCCP3hjTenGFOgWyEFiWg0kkKWuZpnO6MvIjoE"}, "end_date": "2012-08-19T11:48:27.883Z", "slug": "user-timeline", "start_date": "2012-08-19T11:48:27.205Z", "login_type": "oauth", "testrun": 2, "order": 1, "name": "user_timeline"}}, {"pk": 4, "model": "frunner.testcase", "fields": {"result": "success", "exception": null, "login_options": {"consumer_secret": "TnnqvtkvoJqBkFMQnfoWvVxb64ERtHg1AX6mFaEo9hM", "access_token": "767416465-lrGQyTH8xX8zMZEMzCv8s1RKuAqDKXs67HKHAEPM", "consumer_key": "0i4uIl0o03YxeRU6h93pQ", "access_token_secret": "5xHHCCP3hjTenGFOgWyEFiWg0kkKWuZpnO6MvIjoE"}, "end_date": "2012-08-19T11:48:29.166Z", "slug": "post-tweet", "start_date": "2012-08-19T11:48:28.010Z", "login_type": "oauth", "testrun": 2, "order": 1, "name": "post tweet"}}, {"pk": 1, "model": "frunner.testcasestep", "fields": {"exception": null, "response_headers": {"status": "401 Unauthorized", "x-ratelimit-remaining": "134", "via": "1.1 GATE", "x-transaction": "b0fbe2b4cff196e5", "transfer-encoding": "chunked", "set-cookie": "guest_id=\"v1:134537665089679493\"; Expires=Tue, 19-Aug-2014 11:44:10 GMT; Path=/; Domain=.twitter.com", "expires": "Tue, 31 Mar 1981 05:00:00 GMT", "server": "tfe", "last-modified": "Sun, 19 Aug 2012 11:44:10 GMT", "connection": "Keep-Alive, Proxy-Support", "x-ratelimit-limit": "150", "pragma": "no-cache", "cache-control": "no-cache, no-store, must-revalidate, pre-check=0, post-check=0", "date": "Sun, 19 Aug 2012 11:44:10 GMT", "x-frame-options": "SAMEORIGIN", "proxy-support": "Session-Based-Authentication", "content-type": "application/json;charset=utf-8", "www-authenticate": "OAuth realm=\"http://api.twitter.com\"", "x-ratelimit-class": "api", "x-ratelimit-reset": "1345377869"}, "end_date": "2012-08-19T11:44:11.009Z", "url": "statuses/user_timeline.json", "response_body": "{\"request\":\"\\/1\\/statuses\\/user_timeline.json\",\"error\":\"Not authorized\"}", "response_code": 401, "order": 1, "testcase": 1, "method": "GET", "params": "{\"count\": \"{random:1:d}\", \"trim_user\": \"true\", \"screen_name\": \"alarin_ru\"}", "result": "success", "start_date": "2012-08-19T11:44:10.530Z"}}, {"pk": 2, "model": "frunner.testcasestep", "fields": {"exception": null, "response_headers": {"status": "401 Unauthorized", "via": "1.1 GATE", "transfer-encoding": "chunked", "set-cookie": "k=10.35.27.138.1345376651489894; path=/; expires=Sun, 26-Aug-12 11:44:11 GMT; domain=.twitter.com, guest_id=v1%3A134537665149415448; domain=.twitter.com; path=/; expires=Tue, 19-Aug-2014 23:44:11 GMT, _twitter_sess=BAh7CDoPY3JlYXRlZF9hdGwrCOeIsj45AToHaWQiJWNlYjQ1ZDQ0ZmIwOTY2%250AYmZjNzY0NmMxYWMyYzRhMzBmIgpmbGFzaElDOidBY3Rpb25Db250cm9sbGVy%250AOjpGbGFzaDo6Rmxhc2hIYXNoewAGOgpAdXNlZHsA--3b7ac02d91fcf5dd524b3e4fb23a0a17f16878da; domain=.twitter.com; path=/; HttpOnly", "expires": "Sun, 19 Aug 2012 11:49:11 GMT", "connection": "Keep-Alive, Proxy-Support", "server": "tfe", "x-runtime": "0.00287", "cache-control": "no-cache, max-age=300", "date": "Sun, 19 Aug 2012 11:44:11 GMT", "proxy-support": "Session-Based-Authentication", "content-type": "application/json; charset=utf-8", "www-authenticate": "OAuth realm=\"http://api.twitter.com\""}, "end_date": "2012-08-19T11:44:11.609Z", "url": "statuses/update.json", "response_body": "{\"error\":\"Could not authenticate you.\",\"request\":\"\\/1\\/statuses\\/update.json\"}", "response_code": 401, "order": 0, "testcase": 2, "method": "POST", "params": "{\"status\": \"{random:140}\"}", "result": "success", "start_date": "2012-08-19T11:44:11.375Z"}}, {"pk": 3, "model": "frunner.testcasestep", "fields": {"exception": null, "response_headers": {"status": "401 Unauthorized", "x-ratelimit-remaining": "133", "via": "1.1 GATE", "x-transaction": "7bfc55205c16e924", "transfer-encoding": "chunked", "expires": "Tue, 31 Mar 1981 05:00:00 GMT", "server": "tfe", "last-modified": "Sun, 19 Aug 2012 11:44:11 GMT", "connection": "Keep-Alive, Proxy-Support", "x-ratelimit-limit": "150", "pragma": "no-cache", "cache-control": "no-cache, no-store, must-revalidate, pre-check=0, post-check=0", "date": "Sun, 19 Aug 2012 11:44:11 GMT", "x-frame-options": "SAMEORIGIN", "proxy-support": "Session-Based-Authentication", "content-type": "application/json;charset=utf-8", "www-authenticate": "OAuth realm=\"http://api.twitter.com\"", "x-ratelimit-class": "api", "x-ratelimit-reset": "1345377869"}, "end_date": "2012-08-19T11:44:11.958Z", "url": "statuses/user_timeline.json", "response_body": "{\"request\":\"\\/1\\/statuses\\/user_timeline.json\",\"error\":\"Not authorized\"}", "response_code": 401, "order": 1, "testcase": 2, "method": "GET", "params": "", "result": "success", "start_date": "2012-08-19T11:44:11.734Z"}}, {"pk": 4, "model": "frunner.testcasestep", "fields": {"exception": null, "response_headers": {"status": "200 OK", "x-ratelimit-remaining": "348", "via": "1.1 GATE", "proxy-connection": "Keep-Alive", "x-transaction": "ed2923b0dc2eb1b4", "transfer-encoding": "chunked", "set-cookie": "guest_id=\"v1:134537690756205481\"; Expires=Tue, 19-Aug-2014 11:48:27 GMT; Path=/; Domain=.twitter.com, lang=en", "expires": "Tue, 31 Mar 1981 05:00:00 GMT", "x-access-level": "read-write-directmessages", "server": "tfe", "last-modified": "Sun, 19 Aug 2012 11:48:27 GMT", "connection": "Keep-Alive", "x-ratelimit-limit": "350", "pragma": "no-cache", "cache-control": "no-cache, no-store, must-revalidate, pre-check=0, post-check=0", "date": "Sun, 19 Aug 2012 11:48:27 GMT", "x-frame-options": "SAMEORIGIN", "content-type": "application/json;charset=utf-8", "x-ratelimit-class": "api_identified", "x-ratelimit-reset": "1345379952"}, "end_date": "2012-08-19T11:48:27.677Z", "url": "statuses/user_timeline.json", "response_body": "[]", "response_code": 200, "order": 1, "testcase": 3, "method": "GET", "params": "{\"count\": \"{random:1:d}\", \"trim_user\": \"true\", \"screen_name\": \"alarin_ru\"}", "result": "success", "start_date": "2012-08-19T11:48:27.208Z"}}, {"pk": 5, "model": "frunner.testcasestep", "fields": {"exception": null, "response_headers": {"status": "403 Forbidden", "via": "1.1 GATE", "proxy-connection": "Keep-Alive", "x-transaction": "8fb7d7366be92615", "transfer-encoding": "chunked", "x-mid": "2a17b066f0199359d123807e237b4517167e5814", "expires": "Tue, 31 Mar 1981 05:00:00 GMT", "x-access-level": "read-write-directmessages", "connection": "Keep-Alive", "x-transaction-mask": "a6183ffa5f8ca943ff1b53b5644ef114ed625e57", "server": "tfe", "cache-control": "no-cache, no-store, must-revalidate, pre-check=0, post-check=0", "last-modified": "Sun, 19 Aug 2012 11:48:28 GMT", "x-runtime": "0.02374", "pragma": "no-cache", "set-cookie": "k=10.36.36.126.1345376908352558; path=/; expires=Sun, 26-Aug-12 11:48:28 GMT; domain=.twitter.com, guest_id=v1%3A134537690835783645; domain=.twitter.com; path=/; expires=Tue, 19-Aug-2014 23:48:28 GMT, dnt=1; domain=.twitter.com; path=/; expires=Fri, 19-Aug-2022 23:48:28 GMT, pid=; domain=.twitter.com; path=/; expires=Thu, 01-Jan-1970 00:00:00 GMT, lang=en; path=/, twid=u%3D767416465%7CgwGJm0ee8CNAG7sztVkLy6%2Fuk2w%3D; domain=.twitter.com; path=/; secure, _twitter_sess=BAh7CToPY3JlYXRlZF9hdGwrCFF0tj45AToMY3NyZl9pZCIlNzM3YmI3MGJi%250AYjUwZTAwMWY3Y2JjNGRkYzRmMWQ1NWU6B2lkIiU5MTdiOWNlMmU2N2ExZWYx%250AZWI1NmNmMzZjZTQxOWMzMiIKZmxhc2hJQzonQWN0aW9uQ29udHJvbGxlcjo6%250ARmxhc2g6OkZsYXNoSGFzaHsABjoKQHVzZWR7AA%253D%253D--7c00c46964b141087019a965cc2dbf81fb3c7d1a; domain=.twitter.com; path=/; HttpOnly", "date": "Sun, 19 Aug 2012 11:48:28 GMT", "x-frame-options": "SAMEORIGIN", "content-type": "application/json; charset=utf-8"}, "end_date": "2012-08-19T11:48:28.498Z", "url": "statuses/update.json", "response_body": "{\"error\":\"Client must provide a 'status' parameter with a value.\",\"request\":\"\\/1\\/statuses\\/update.json\"}", "response_code": 403, "order": 0, "testcase": 4, "method": "POST", "params": "{\"status\": \"{random:140}\"}", "result": "success", "start_date": "2012-08-19T11:48:28.012Z"}}, {"pk": 6, "model": "frunner.testcasestep", "fields": {"exception": null, "response_headers": {"status": "200 OK", "x-ratelimit-remaining": "347", "via": "1.1 GATE", "proxy-connection": "Keep-Alive", "x-transaction": "51334cbe1bd60ef9", "transfer-encoding": "chunked", "expires": "Tue, 31 Mar 1981 05:00:00 GMT", "x-access-level": "read-write-directmessages", "server": "tfe", "last-modified": "Sun, 19 Aug 2012 11:48:28 GMT", "connection": "Keep-Alive", "x-ratelimit-limit": "350", "pragma": "no-cache", "cache-control": "no-cache, no-store, must-revalidate, pre-check=0, post-check=0", "date": "Sun, 19 Aug 2012 11:48:28 GMT", "x-frame-options": "SAMEORIGIN", "content-type": "application/json;charset=utf-8", "x-ratelimit-class": "api_identified", "x-ratelimit-reset": "1345379952"}, "end_date": "2012-08-19T11:48:28.913Z", "url": "statuses/user_timeline.json", "response_body": "[]", "response_code": 200, "order": 1, "testcase": 4, "method": "GET", "params": "", "result": "success", "start_date": "2012-08-19T11:48:28.621Z"}}, {"pk": 19, "model": "auth.permission", "fields": {"codename": "add_logentry", "name": "Can add log entry", "content_type": 7}}, {"pk": 20, "model": "auth.permission", "fields": {"codename": "change_logentry", "name": "Can change log entry", "content_type": 7}}, {"pk": 21, "model": "auth.permission", "fields": {"codename": "delete_logentry", "name": "Can delete log entry", "content_type": 7}}, {"pk": 1, "model": "auth.permission", "fields": {"codename": "add_group", "name": "Can add group", "content_type": 2}}, {"pk": 4, "model": "auth.permission", "fields": {"codename": "change_group", "name": "Can change group", "content_type": 2}}, {"pk": 7, "model": "auth.permission", "fields": {"codename": "delete_group", "name": "Can delete group", "content_type": 2}}, {"pk": 2, "model": "auth.permission", "fields": {"codename": "add_permission", "name": "Can add permission", "content_type": 1}}, {"pk": 5, "model": "auth.permission", "fields": {"codename": "change_permission", "name": "Can change permission", "content_type": 1}}, {"pk": 8, "model": "auth.permission", "fields": {"codename": "delete_permission", "name": "Can delete permission", "content_type": 1}}, {"pk": 3, "model": "auth.permission", "fields": {"codename": "add_user", "name": "Can add user", "content_type": 3}}, {"pk": 6, "model": "auth.permission", "fields": {"codename": "change_user", "name": "Can change user", "content_type": 3}}, {"pk": 9, "model": "auth.permission", "fields": {"codename": "delete_user", "name": "Can delete user", "content_type": 3}}, {"pk": 10, "model": "auth.permission", "fields": {"codename": "add_contenttype", "name": "Can add content type", "content_type": 4}}, {"pk": 11, "model": "auth.permission", "fields": {"codename": "change_contenttype", "name": "Can change content type", "content_type": 4}}, {"pk": 12, "model": "auth.permission", "fields": {"codename": "delete_contenttype", "name": "Can delete content type", "content_type": 4}}, {"pk": 49, "model": "auth.permission", "fields": {"codename": "add_message", "name": "Can add message", "content_type": 18}}, {"pk": 51, "model": "auth.permission", "fields": {"codename": "change_message", "name": "Can change message", "content_type": 18}}, {"pk": 53, "model": "auth.permission", "fields": {"codename": "delete_message", "name": "Can delete message", "content_type": 18}}, {"pk": 50, "model": "auth.permission", "fields": {"codename": "add_queue", "name": "Can add queue", "content_type": 17}}, {"pk": 52, "model": "auth.permission", "fields": {"codename": "change_queue", "name": "Can change queue", "content_type": 17}}, {"pk": 54, "model": "auth.permission", "fields": {"codename": "delete_queue", "name": "Can delete queue", "content_type": 17}}, {"pk": 25, "model": "auth.permission", "fields": {"codename": "add_crontabschedule", "name": "Can add crontab", "content_type": 12}}, {"pk": 33, "model": "auth.permission", "fields": {"codename": "change_crontabschedule", "name": "Can change crontab", "content_type": 12}}, {"pk": 41, "model": "auth.permission", "fields": {"codename": "delete_crontabschedule", "name": "Can delete crontab", "content_type": 12}}, {"pk": 26, "model": "auth.permission", "fields": {"codename": "add_intervalschedule", "name": "Can add interval", "content_type": 11}}, {"pk": 34, "model": "auth.permission", "fields": {"codename": "change_intervalschedule", "name": "Can change interval", "content_type": 11}}, {"pk": 42, "model": "auth.permission", "fields": {"codename": "delete_intervalschedule", "name": "Can delete interval", "content_type": 11}}, {"pk": 27, "model": "auth.permission", "fields": {"codename": "add_periodictask", "name": "Can add periodic task", "content_type": 14}}, {"pk": 35, "model": "auth.permission", "fields": {"codename": "change_periodictask", "name": "Can change periodic task", "content_type": 14}}, {"pk": 43, "model": "auth.permission", "fields": {"codename": "delete_periodictask", "name": "Can delete periodic task", "content_type": 14}}, {"pk": 28, "model": "auth.permission", "fields": {"codename": "add_periodictasks", "name": "Can add periodic tasks", "content_type": 13}}, {"pk": 36, "model": "auth.permission", "fields": {"codename": "change_periodictasks", "name": "Can change periodic tasks", "content_type": 13}}, {"pk": 44, "model": "auth.permission", "fields": {"codename": "delete_periodictasks", "name": "Can delete periodic tasks", "content_type": 13}}, {"pk": 31, "model": "auth.permission", "fields": {"codename": "add_taskmeta", "name": "Can add task state", "content_type": 9}}, {"pk": 39, "model": "auth.permission", "fields": {"codename": "change_taskmeta", "name": "Can change task state", "content_type": 9}}, {"pk": 47, "model": "auth.permission", "fields": {"codename": "delete_taskmeta", "name": "Can delete task state", "content_type": 9}}, {"pk": 29, "model": "auth.permission", "fields": {"codename": "add_tasksetmeta", "name": "Can add saved group result", "content_type": 10}}, {"pk": 37, "model": "auth.permission", "fields": {"codename": "change_tasksetmeta", "name": "Can change saved group result", "content_type": 10}}, {"pk": 45, "model": "auth.permission", "fields": {"codename": "delete_tasksetmeta", "name": "Can delete saved group result", "content_type": 10}}, {"pk": 30, "model": "auth.permission", "fields": {"codename": "add_taskstate", "name": "Can add task", "content_type": 16}}, {"pk": 38, "model": "auth.permission", "fields": {"codename": "change_taskstate", "name": "Can change task", "content_type": 16}}, {"pk": 46, "model": "auth.permission", "fields": {"codename": "delete_taskstate", "name": "Can delete task", "content_type": 16}}, {"pk": 32, "model": "auth.permission", "fields": {"codename": "add_workerstate", "name": "Can add worker", "content_type": 15}}, {"pk": 40, "model": "auth.permission", "fields": {"codename": "change_workerstate", "name": "Can change worker", "content_type": 15}}, {"pk": 48, "model": "auth.permission", "fields": {"codename": "delete_workerstate", "name": "Can delete worker", "content_type": 15}}, {"pk": 55, "model": "auth.permission", "fields": {"codename": "add_company", "name": "Can add company", "content_type": 19}}, {"pk": 57, "model": "auth.permission", "fields": {"codename": "change_company", "name": "Can change company", "content_type": 19}}, {"pk": 59, "model": "auth.permission", "fields": {"codename": "delete_company", "name": "Can delete company", "content_type": 19}}, {"pk": 56, "model": "auth.permission", "fields": {"codename": "add_fortuitusprofile", "name": "Can add fortuitus profile", "content_type": 20}}, {"pk": 58, "model": "auth.permission", "fields": {"codename": "change_fortuitusprofile", "name": "Can change fortuitus profile", "content_type": 20}}, {"pk": 60, "model": "auth.permission", "fields": {"codename": "delete_fortuitusprofile", "name": "Can delete fortuitus profile", "content_type": 20}}, {"pk": 61, "model": "auth.permission", "fields": {"codename": "add_testcase", "name": "Can add test case", "content_type": 22}}, {"pk": 65, "model": "auth.permission", "fields": {"codename": "change_testcase", "name": "Can change test case", "content_type": 22}}, {"pk": 69, "model": "auth.permission", "fields": {"codename": "delete_testcase", "name": "Can delete test case", "content_type": 22}}, {"pk": 62, "model": "auth.permission", "fields": {"codename": "add_testcaseassert", "name": "Can add test case assert", "content_type": 24}}, {"pk": 66, "model": "auth.permission", "fields": {"codename": "change_testcaseassert", "name": "Can change test case assert", "content_type": 24}}, {"pk": 70, "model": "auth.permission", "fields": {"codename": "delete_testcaseassert", "name": "Can delete test case assert", "content_type": 24}}, {"pk": 63, "model": "auth.permission", "fields": {"codename": "add_testcasestep", "name": "Can add test case step", "content_type": 23}}, {"pk": 67, "model": "auth.permission", "fields": {"codename": "change_testcasestep", "name": "Can change test case step", "content_type": 23}}, {"pk": 71, "model": "auth.permission", "fields": {"codename": "delete_testcasestep", "name": "Can delete test case step", "content_type": 23}}, {"pk": 64, "model": "auth.permission", "fields": {"codename": "add_testproject", "name": "Can add test project", "content_type": 21}}, {"pk": 68, "model": "auth.permission", "fields": {"codename": "change_testproject", "name": "Can change test project", "content_type": 21}}, {"pk": 72, "model": "auth.permission", "fields": {"codename": "delete_testproject", "name": "Can delete test project", "content_type": 21}}, {"pk": 73, "model": "auth.permission", "fields": {"codename": "add_testcase", "name": "Can add test case", "content_type": 26}}, {"pk": 77, "model": "auth.permission", "fields": {"codename": "change_testcase", "name": "Can change test case", "content_type": 26}}, {"pk": 81, "model": "auth.permission", "fields": {"codename": "delete_testcase", "name": "Can delete test case", "content_type": 26}}, {"pk": 74, "model": "auth.permission", "fields": {"codename": "add_testcaseassert", "name": "Can add test case assert", "content_type": 28}}, {"pk": 78, "model": "auth.permission", "fields": {"codename": "change_testcaseassert", "name": "Can change test case assert", "content_type": 28}}, {"pk": 82, "model": "auth.permission", "fields": {"codename": "delete_testcaseassert", "name": "Can delete test case assert", "content_type": 28}}, {"pk": 75, "model": "auth.permission", "fields": {"codename": "add_testcasestep", "name": "Can add test case step", "content_type": 27}}, {"pk": 79, "model": "auth.permission", "fields": {"codename": "change_testcasestep", "name": "Can change test case step", "content_type": 27}}, {"pk": 83, "model": "auth.permission", "fields": {"codename": "delete_testcasestep", "name": "Can delete test case step", "content_type": 27}}, {"pk": 76, "model": "auth.permission", "fields": {"codename": "add_testrun", "name": "Can add test run", "content_type": 25}}, {"pk": 80, "model": "auth.permission", "fields": {"codename": "change_testrun", "name": "Can change test run", "content_type": 25}}, {"pk": 84, "model": "auth.permission", "fields": {"codename": "delete_testrun", "name": "Can delete test run", "content_type": 25}}, {"pk": 13, "model": "auth.permission", "fields": {"codename": "add_session", "name": "Can add session", "content_type": 5}}, {"pk": 14, "model": "auth.permission", "fields": {"codename": "change_session", "name": "Can change session", "content_type": 5}}, {"pk": 15, "model": "auth.permission", "fields": {"codename": "delete_session", "name": "Can delete session", "content_type": 5}}, {"pk": 16, "model": "auth.permission", "fields": {"codename": "add_site", "name": "Can add site", "content_type": 6}}, {"pk": 17, "model": "auth.permission", "fields": {"codename": "change_site", "name": "Can change site", "content_type": 6}}, {"pk": 18, "model": "auth.permission", "fields": {"codename": "delete_site", "name": "Can delete site", "content_type": 6}}, {"pk": 22, "model": "auth.permission", "fields": {"codename": "add_migrationhistory", "name": "Can add migration history", "content_type": 8}}, {"pk": 23, "model": "auth.permission", "fields": {"codename": "change_migrationhistory", "name": "Can change migration history", "content_type": 8}}, {"pk": 24, "model": "auth.permission", "fields": {"codename": "delete_migrationhistory", "name": "Can delete migration history", "content_type": 8}}, {"pk": 1, "model": "auth.user", "fields": {"username": "root", "first_name": "", "last_name": "", "is_active": true, "is_superuser": true, "is_staff": true, "last_login": "2012-08-19T05:00:03.033Z", "groups": [], "user_permissions": [], "password": "pbkdf2_sha256$10000$4wiz8Ofv42Tb$/GSJmyZIKeJY3zlwXOobjL3Lq9elDXfpsuTolwxJep4=", "email": "root@example.com", "date_joined": "2012-08-19T04:59:52.447Z"}}, {"pk": 2, "model": "auth.user", "fields": {"username": "demo1", "first_name": "", "last_name": "", "is_active": true, "is_superuser": false, "is_staff": false, "last_login": "2012-08-19T05:00:18Z", "groups": [], "user_permissions": [], "password": "pbkdf2_sha256$10000$ZuipM0rarRua$8IECDwYWTYAbhSRnI9p/rpXCXKgZ4u2XAK+k5mNU828=", "email": "", "date_joined": "2012-08-19T05:00:18Z"}}, {"pk": 3, "model": "auth.user", "fields": {"username": "demo2", "first_name": "", "last_name": "", "is_active": true, "is_superuser": false, "is_staff": false, "last_login": "2012-08-19T05:00:24Z", "groups": [], "user_permissions": [], "password": "pbkdf2_sha256$10000$uVn0JtjDGg7O$52tAMs8l8tFNk5r/1LyYnAA1OhJuGgcva825GqVcTbY=", "email": "", "date_joined": "2012-08-19T05:00:24Z"}}, {"pk": 1, "model": "fcore.fortuitusprofile", "fields": {"company": 1, "user": 1}}, {"pk": 2, "model": "fcore.fortuitusprofile", "fields": {"company": 1, "user": 2}}, {"pk": 3, "model": "fcore.fortuitusprofile", "fields": {"company": 2, "user": 3}}]