[
  {
    "pk":1,
    "model":"auth.user",
    "fields":{
      "username":"root",
      "first_name":"",
      "last_name":"",
      "is_active":true,
      "is_superuser":true,
      "is_staff":true,
      "last_login":"2012-08-19T05:00:03.033Z",
      "groups":[],
      "user_permissions":[],
      "password":"pbkdf2_sha256$10000$4wiz8Ofv42Tb$/GSJmyZIKeJY3zlwXOobjL3Lq9elDXfpsuTolwxJep4=",
      "email":"root@example.com",
      "date_joined":"2012-08-19T04:59:52.447Z"
    }
  },
  {
    "pk":2,
    "model":"auth.user",
    "fields":{
      "username":"demo1",
      "first_name":"",
      "last_name":"",
      "is_active":true,
      "is_superuser":false,
      "is_staff":false,
      "last_login":"2012-08-19T05:00:18Z",
      "groups":[],
      "user_permissions":[],
      "password":"pbkdf2_sha256$10000$ZuipM0rarRua$8IECDwYWTYAbhSRnI9p/rpXCXKgZ4u2XAK+k5mNU828=",
      "email":"",
      "date_joined":"2012-08-19T05:00:18Z"
    }
  },
  {
    "pk":3,
    "model":"auth.user",
    "fields":{
      "username":"demo2",
      "first_name":"",
      "last_name":"",
      "is_active":true,
      "is_superuser":false,
      "is_staff":false,
      "last_login":"2012-08-19T05:00:24Z",
      "groups":[],
      "user_permissions":[],
      "password":"pbkdf2_sha256$10000$uVn0JtjDGg7O$52tAMs8l8tFNk5r/1LyYnAA1OhJuGgcva825GqVcTbY=",
      "email":"",
      "date_joined":"2012-08-19T05:00:24Z"
    }
  },
  {
    "pk":4,
    "model":"auth.user",
    "fields":{
      "username":"demo",
      "first_name":"",
      "last_name":"",
      "is_active":true,
      "is_superuser":false,
      "is_staff":false,
      "last_login":"2012-08-19T15:29:31.730Z",
      "groups":[],
      "user_permissions":[],
      "password":"pbkdf2_sha256$10000$a9ydcnWQZi3U$QSUFnfTklITfKPXPCYNUwydOGhX+SE3QSoT/iWcLh74=",
      "email":"",
      "date_joined":"2012-08-19T15:29:31.162Z"
    }
  },
  {
    "pk":1,
    "model":"fcore.company",
    "fields":{
      "slug":"demo",
      "name":"demo"
    }
  },
  {
    "pk":2,
    "model":"fcore.company",
    "fields":{
      "slug":"demo-org-2",
      "name":"demo org 2"
    }
  },
  {
    "pk":1,
    "model":"fcore.fortuitusprofile",
    "fields":{
      "company":1,
      "user":1
    }
  },
  {
    "pk":2,
    "model":"fcore.fortuitusprofile",
    "fields":{
      "company":1,
      "user":2
    }
  },
  {
    "pk":3,
    "model":"fcore.fortuitusprofile",
    "fields":{
      "company":2,
      "user":3
    }
  },
  {
    "pk":4,
    "model":"fcore.fortuitusprofile",
    "fields":{
      "company":1,
      "user":4
    }
  }
]